orma/__init__.py
orma/__main__.py
orma-0.2507.0.dist-info/METADATA
orma-0.2507.0.dist-info/WHEEL
orma-0.2507.0.dist-info/entry_points.txt
orma-0.2507.0.dist-info/top_level.txt
orma-0.2507.0.dist-info/RECORD
